CellMet/__init__.py
CellMet/_version.py
CellMet/analysis.py
CellMet/image.py
CellMet/io.py
CellMet/plot.py
CellMet/segmentation.py
CellMet/segmentation2D.py
CellMet/utils.py
CellMet/version.py
CellSeg/__init__.py
CellSeg/analysis.py
CellSeg/image.py
CellSeg/io.py
CellSeg/plot.py
CellSeg/segmentation.py
CellSeg/segmentation2D.py
CellSeg/utils.py
cellmet-1.1.0.dist-info/licenses/LICENSE
cellmet-1.1.0.dist-info/METADATA
cellmet-1.1.0.dist-info/WHEEL
cellmet-1.1.0.dist-info/top_level.txt
cellmet-1.1.0.dist-info/RECORD
